huscy/subject_notes/__init__.py
huscy/subject_notes/admin.py
huscy/subject_notes/apps.py
huscy/subject_notes/models.py
huscy/subject_notes/permissions.py
huscy/subject_notes/serializer.py
huscy/subject_notes/services.py
huscy/subject_notes/urls.py
huscy/subject_notes/views.py
huscy/subject_notes/migrations/.gitignore
huscy/subject_notes/migrations/0001_initial.py
huscy/subject_notes/migrations/__init__.py
huscy_subject_notes-0.1.0a5.dist-info/METADATA
huscy_subject_notes-0.1.0a5.dist-info/WHEEL
huscy_subject_notes-0.1.0a5.dist-info/licenses/LICENSE
huscy_subject_notes-0.1.0a5.dist-info/RECORD
